setup.py
fill_missing_101703384/__init__.py
fill_missing_101703384/fill_missing.py
fill_missing_101703384.egg-info/PKG-INFO
fill_missing_101703384.egg-info/SOURCES.txt
fill_missing_101703384.egg-info/dependency_links.txt
fill_missing_101703384.egg-info/entry_points.txt
fill_missing_101703384.egg-info/requires.txt
fill_missing_101703384.egg-info/top_level.txt