Metadata-Version: 1.1
Name: fill-missing-101703384
Version: 1.1
Summary: PROJECT 3, Submitted By: Parteek Sharma(101703384), COE18
Home-page: UNKNOWN
Author: Parteek Sharma
Author-email: psharma_be17@thapar.edu
License: MIT
Keywords: replace missing values,missing values,impute missing values
Platform: UNKNOWN
Classifier: Development Status :: 3 - Alpha
Classifier: Intended Audience :: Developers
Classifier: Topic :: Software Development :: Build Tools
Classifier: License :: OSI Approved :: MIT License
Classifier: Programming Language :: Python :: 3
Classifier: Programming Language :: Python :: 3.4
Classifier: Programming Language :: Python :: 3.5
Classifier: Programming Language :: Python :: 3.6
Classifier: Programming Language :: Python :: 3.6
